svd_by_viikoshh/main.py
svd_by_viikoshh/SVD.py
svd_by_viikoshh-0.1.0.dist-info/entry_points.txt
svd_by_viikoshh-0.1.0.dist-info/WHEEL
svd_by_viikoshh-0.1.0.dist-info/METADATA
svd_by_viikoshh-0.1.0.dist-info/RECORD
