Metadata-Version: 2.1
Name: svd-by-viikoshh
Version: 0.1.0
Summary: SVD
Author: viikoshh
Author-email: 105398417+viikoshh@users.noreply.github.com
Requires-Python: >=3.11,<4.0
Classifier: Programming Language :: Python :: 3
Classifier: Programming Language :: Python :: 3.11
Requires-Dist: numpy (>=1.24.1,<2.0.0)
